CHANGES.txt
DEPENDENCES.txt
README.txt
setup.py
src/__init__.py
src/ng/__init__.py
src/ng.site.addon.extension.egg-info/PKG-INFO
src/ng.site.addon.extension.egg-info/SOURCES.txt
src/ng.site.addon.extension.egg-info/dependency_links.txt
src/ng.site.addon.extension.egg-info/namespace_packages.txt
src/ng.site.addon.extension.egg-info/not-zip-safe
src/ng.site.addon.extension.egg-info/requires.txt
src/ng.site.addon.extension.egg-info/top_level.txt
src/ng/site/__init__.py
src/ng/site/addon/__init__.py
src/ng/site/addon/extension/__init__.py
src/ng/site/addon/extension/configure.zcml
src/ng/site/addon/extension/ng.site.addon.extension.txt
src/ng/site/addon/extension/etc/ng.site.addon.extension-configure.zcml
src/ng/site/addon/extension/fuzzytraverser/__init__.py
src/ng/site/addon/extension/fuzzytraverser/configure.zcml
src/ng/site/addon/extension/install/__init__.py
src/ng/site/addon/extension/install/configure.zcml
src/ng/site/addon/extension/install/install_fuzzytraverser.py
src/ng/site/addon/extension/install/install_quota.py
src/ng/site/addon/extension/quota/__init__.py
src/ng/site/addon/extension/quota/configure.zcml