Metadata-Version: 1.0
Name: ng.site.addon.extension
Version: 1.1.4
Summary: Extension add-on for simple content-site
Home-page: http://www.dreambot.ru/product/DreamBotSite/ng.site.addon.extension/
Author: Andrey Orlov
Author-email: dbdt@dreambot.ru
License: GPL v2.1
Platform: UNKNOWN
Classifier: Environment :: Web Environment
Classifier: Intended Audience :: Developers
Classifier: License :: OSI Approved :: GNU General Public License (GPL)
Classifier: Programming Language :: Python
Classifier: Operating System :: OS Independent
Classifier: Topic :: Internet :: WWW/HTTP
Classifier: Framework :: Zope3
